setup.py
broccoli/__init__.py
broccoli/core.py
broccoli/flask.py
broccoli/utils.py
broccoli.egg-info/PKG-INFO
broccoli.egg-info/SOURCES.txt
broccoli.egg-info/dependency_links.txt
broccoli.egg-info/top_level.txt