Metadata-Version: 1.1
Name: broccoli
Version: 1.0.0
Summary: A simple dependency injection package based on type annotations
Home-page: https://github.com/msoedov/broccoli
Author: Alex Myasoedov
Author-email: msoedov@gmail.com
License: MIT
Keywords: dependency injection
Platform: UNKNOWN
Classifier: Development Status :: 2 - Pre-Alpha
Classifier: Intended Audience :: Developers
Classifier: Operating System :: OS Independent
Classifier: Topic :: Software Development :: Libraries
Classifier: License :: OSI Approved :: MIT License
Classifier: Intended Audience :: Developers
Classifier: Programming Language :: Python :: 3
Classifier: Programming Language :: Python :: 3 :: Only
Classifier: Programming Language :: Python :: 3.2
Classifier: Programming Language :: Python :: 3.3
Classifier: Programming Language :: Python :: 3.4
Classifier: Programming Language :: Python :: 3.5
